<?xml version="1.0"?>
<mysqldump xmlns:xsi="http://www.w3.org/2001/XMLSchema-instance">
 <database name="">
  <table_structure name="#__content_frontpage">
   <field Field="content_id" Type="int" Null="NO" Key="PRI" Default="0" Extra="" />
   <field Field="ordering" Type="int" Null="NO" Key="" Default="0" Extra="" />
   <field Field="featured_up" Type="datetime" Null="YES" Key="" Extra="" />
   <field Field="featured_down" Type="datetime" Null="YES" Key="" Extra="" />
   <key Table="#__content_frontpage" Non_unique="0" Key_name="PRIMARY" Seq_in_index="1" Column_name="content_id" Collation="A" Null="" Index_type="BTREE" Sub_part="" Comment="" />
  </table_structure>
 </database>
</mysqldump>