<?xml version="1.0"?>
<mysqldump xmlns:xsi="http://www.w3.org/2001/XMLSchema-instance">
 <database name="">
  <table_structure name="#__finder_tokens_aggregate">
   <field Field="term_id" Type="int unsigned" Null="NO" Key="MUL" Extra="" />
   <field Field="term" Type="varchar(75)" Null="NO" Key="MUL" Extra="" />
   <field Field="stem" Type="varchar(75)" Null="NO" Key="" Default="" Extra="" />
   <field Field="common" Type="tinyint unsigned" Null="NO" Key="" Default="0" Extra="" />
   <field Field="phrase" Type="tinyint unsigned" Null="NO" Key="" Default="0" Extra="" />
   <field Field="term_weight" Type="float unsigned" Null="NO" Key="" Default="0" Extra="" />
   <field Field="context" Type="tinyint unsigned" Null="NO" Key="" Default="2" Extra="" />
   <field Field="context_weight" Type="float unsigned" Null="NO" Key="" Default="0" Extra="" />
   <field Field="total_weight" Type="float unsigned" Null="NO" Key="" Default="0" Extra="" />
   <field Field="language" Type="char(7)" Null="NO" Key="" Default="" Extra="" />
   <key Table="#__finder_tokens_aggregate" Non_unique="1" Key_name="token" Seq_in_index="1" Column_name="term" Collation="A" Null="" Index_type="BTREE" Sub_part="" Comment="" />
   <key Table="#__finder_tokens_aggregate" Non_unique="1" Key_name="keyword_id" Seq_in_index="1" Column_name="term_id" Collation="A" Null="" Index_type="BTREE" Sub_part="" Comment="" />
  </table_structure>
 </database>
</mysqldump>